stpkg/__init__.py
stpkg/__main__ .py
stpkg/setuptest.py
stpkg/starterclass.py
stpkg/Conf/__init__.py
stpkg/Conf/test_configVars.py
stpkg/Pages/GateCls.py
stpkg/Pages/IndexCls.py
stpkg/Pages/OnlineAssessmentCls.py
stpkg/Pages/OverviewCls.py
stpkg/Pages/ProjectRegisterCls.py
stpkg/Pages/RegisterCls.py
stpkg/Pages/ThreadviewCls.py
stpkg/Pages/__init__.py
stpkg/Pages/ccs_projectsManagementCls.py
stpkg/Pages/newWBSelementCls.py
stpkg/Pages/persProfileCls.py
stpkg/RunSetups/__init__.py
stpkg/RunSetups/test_ini_1_createTables.py
stpkg/RunSetups/test_ini_2_registerSuperadmin.py
stpkg/RunSetups/test_ini_3_1stProjectSetup.py
stpkg/RunSetups/test_ini_4_4ProjectsSetup.py
stpkg/Tests/__init__.py
stpkg/Tests/test_loginCreateProjectCreateWBS.py
stpkg/Tests/test_loginMakePosts.py
stpkg/Tests/test_loginPersProfileComplete.py
setuptest-1.1.7.dist-info/LICENSE
setuptest-1.1.7.dist-info/METADATA
setuptest-1.1.7.dist-info/WHEEL
setuptest-1.1.7.dist-info/entry_points.txt
setuptest-1.1.7.dist-info/top_level.txt
setuptest-1.1.7.dist-info/RECORD
