Metadata-Version: 2.1
Name: setuptest
Version: 1.1.7
Summary: The Selenium based setuptest for the CYBR CSCW-SUITE (CCS) - check the README.md to follow the steps for making it run from your PyCharm IDE
Home-page: https://c-c-s.sourceforge.io/
Author: Florian Strahberger
Author-email: flori@ctemplar.com
License: MIT
Keywords: CYBR CSCW-SUITE,CCS,digital workplace,project management,digitalization,communication,collaboration,groupware,setup.install,test,selenium,pytest,chromedriver,setuptest
Platform: UNKNOWN
Classifier: License :: OSI Approved :: MIT License
Classifier: Programming Language :: Python :: 3
Classifier: Programming Language :: Python :: 3.6
Requires-Dist: atomicwrites (==1.3.0)
Requires-Dist: attrs (==19.3.0)
Requires-Dist: importlib-metadata (==0.23)
Requires-Dist: more-itertools (==7.2.0)
Requires-Dist: packaging (==19.2)
Requires-Dist: pluggy (==0.13.0)
Requires-Dist: py (==1.8.0)
Requires-Dist: pyparsing (==2.4.2)
Requires-Dist: pytest (==5.2.2)
Requires-Dist: selenium (==3.141.0)
Requires-Dist: six (==1.12.0)
Requires-Dist: urllib3 (==1.25.6)
Requires-Dist: wcwidth (==0.1.7)
Requires-Dist: zipp (==0.6.0)
